selenium/__init__.py
selenium/py.typed
selenium/types.py
selenium/common/__init__.py
selenium/common/exceptions.py
selenium/webdriver/__init__.py
selenium/webdriver/chrome/__init__.py
selenium/webdriver/chrome/options.py
selenium/webdriver/chrome/service.py
selenium/webdriver/chrome/webdriver.py
selenium/webdriver/chromium/__init__.py
selenium/webdriver/chromium/options.py
selenium/webdriver/chromium/remote_connection.py
selenium/webdriver/chromium/service.py
selenium/webdriver/chromium/webdriver.py
selenium/webdriver/common/__init__.py
selenium/webdriver/common/action_chains.py
selenium/webdriver/common/alert.py
selenium/webdriver/common/by.py
selenium/webdriver/common/desired_capabilities.py
selenium/webdriver/common/keys.py
selenium/webdriver/common/log.py
selenium/webdriver/common/options.py
selenium/webdriver/common/print_page_options.py
selenium/webdriver/common/proxy.py
selenium/webdriver/common/selenium_manager.py
selenium/webdriver/common/service.py
selenium/webdriver/common/timeouts.py
selenium/webdriver/common/utils.py
selenium/webdriver/common/virtual_authenticator.py
selenium/webdriver/common/window.py
selenium/webdriver/common/actions/__init__.py
selenium/webdriver/common/actions/action_builder.py
selenium/webdriver/common/actions/input_device.py
selenium/webdriver/common/actions/interaction.py
selenium/webdriver/common/actions/key_actions.py
selenium/webdriver/common/actions/key_input.py
selenium/webdriver/common/actions/mouse_button.py
selenium/webdriver/common/actions/pointer_actions.py
selenium/webdriver/common/actions/pointer_input.py
selenium/webdriver/common/actions/wheel_actions.py
selenium/webdriver/common/actions/wheel_input.py
selenium/webdriver/common/bidi/__init__.py
selenium/webdriver/common/bidi/cdp.py
selenium/webdriver/common/bidi/console.py
selenium/webdriver/common/devtools/v107/__init__.py
selenium/webdriver/common/devtools/v107/accessibility.py
selenium/webdriver/common/devtools/v107/animation.py
jyl_selenium-4.8.1.dist-info/METADATA
jyl_selenium-4.8.1.dist-info/WHEEL
jyl_selenium-4.8.1.dist-info/top_level.txt
jyl_selenium-4.8.1.dist-info/RECORD
