Metadata-Version: 2.1
Name: jyl-selenium
Version: 4.8.1
Summary: jyl Python bindings for Selenium
Home-page: https://github.com/SeleniumHQ/selenium/
License: Apache 2.0
Project-URL: Bug Tracker, https://github.com/SeleniumHQ/selenium/issues
Project-URL: Changes, https://github.com/SeleniumHQ/selenium/blob/trunk/py/CHANGES
Project-URL: Documentation, https://www.selenium.dev/documentation/overview/
Project-URL: Source Code, https://github.com/SeleniumHQ/selenium/tree/trunk/py
Classifier: Development Status :: 5 - Production/Stable
Classifier: Intended Audience :: Developers
Classifier: License :: OSI Approved :: Apache Software License
Classifier: Operating System :: POSIX
Classifier: Operating System :: Microsoft :: Windows
Classifier: Operating System :: MacOS :: MacOS X
Classifier: Topic :: Software Development :: Testing
Classifier: Topic :: Software Development :: Libraries
Classifier: Programming Language :: Python
Classifier: Programming Language :: Python :: 3.7
Classifier: Programming Language :: Python :: 3.8
Classifier: Programming Language :: Python :: 3.9
Requires-Python: ~=3.7
Requires-Dist: urllib3[socks] (~=1.26)
Requires-Dist: trio (~=0.17)
Requires-Dist: trio-websocket (~=0.9)
Requires-Dist: certifi (>=2021.10.8)
